nonebot_plugin_twitter/__init__.py
nonebot_plugin_twitter/api.py
nonebot_plugin_twitter/config.py
nonebot_plugin_twitter-0.2.4.dist-info/WHEEL
nonebot_plugin_twitter-0.2.4.dist-info/METADATA
nonebot_plugin_twitter-0.2.4.dist-info/licenses/LICENSE
nonebot_plugin_twitter-0.2.4.dist-info/RECORD
