Metadata-Version: 2.1
Name: nonebot-plugin-twitter
Version: 0.2.4
Summary: NoneBot2 plugin for twitter
License: MIT
Author-email: nek0us <nekouss@gmail.com>
Requires-Python: >=3.8
Requires-Dist: beautifulsoup4>=4.11.1
Requires-Dist: httpx>=0.23.0
Requires-Dist: httpx[http2]>=0.25.0
Requires-Dist: nonebot-adapter-onebot>=2.1.3
Requires-Dist: nonebot2>=2.0.0
Requires-Dist: nonebot_plugin_apscheduler>=0.2.0
Requires-Dist: nonebot_plugin_sendmsg_by_bots>=0.0.4
Requires-Dist: playwright
Project-URL: Homepage, https://github.com/nek0us/nonebot-plugin-twitter
Project-URL: Repository, https://github.com/nek0us/nonebot-plugin-twitter
